datagen/__init__.py
datagen/generator.py
datagen/db/__init__.py
datagen/db/mysql.py
datagen/maker/__init__.py
datagen/maker/dtype.py
datagen/maker/maker.py
datagen/maker/unique.py
datagen_mysql-0.0.2.dist-info/LICENSE
datagen_mysql-0.0.2.dist-info/METADATA
datagen_mysql-0.0.2.dist-info/WHEEL
datagen_mysql-0.0.2.dist-info/top_level.txt
datagen_mysql-0.0.2.dist-info/RECORD
