Metadata-Version: 2.1
Name: datagen-mysql
Version: 0.0.2
Summary: MySQL Data Generator
Home-page: https://github.com/wklee610/datagen
Author: Hajun Lee
Author-email: wklee610@gmail.com
Classifier: Programming Language :: Python :: 3.8
Classifier: Programming Language :: Python :: 3.9
Classifier: Programming Language :: Python :: 3.10
Classifier: Programming Language :: Python :: 3.11
Classifier: License :: OSI Approved :: MIT License
Classifier: Operating System :: OS Independent
Requires-Python: >=3.7
License-File: LICENSE
Requires-Dist: pymysql
